{
    "os": "macOS-10.16-x86_64-i386-64bit",
    "python": "3.9.7",
    "heartbeatAt": "2023-01-13T11:15:10.158187",
    "startedAt": "2023-01-13T11:15:09.345013",
    "docker": null,
    "cuda": null,
    "args": [],
    "state": "running",
    "program": "/Users/abdulrahman/Documents/DTU/mlops/dtu_mlops/mnist_project/src/models/train_model.py",
    "codePath": "mnist_project/src/models/train_model.py",
    "git": {
        "remote": "git@github.com:abdualrhman/dtu_mlops.git",
        "commit": "f3a29d9f7b6a9431c05c32360d7a71b684201276"
    },
    "email": "abdulrahman.ramdan@outlook.com",
    "root": "/Users/abdulrahman/Documents/DTU/mlops/dtu_mlops",
    "host": "abdulrahmansmbp.students.clients.local",
    "username": "abdulrahman",
    "executable": "/Users/abdulrahman/opt/anaconda3/bin/python",
    "cpu_count": 8,
    "cpu_count_logical": 8,
    "cpu_freq": {
        "current": 2400,
        "min": 2400,
        "max": 2400
    },
    "cpu_freq_per_core": [
        {
            "current": 2400,
            "min": 2400,
            "max": 2400
        }
    ],
    "disk": {
        "total": 228.27386474609375,
        "used": 20.826148986816406
    },
    "memory": {
        "total": 16.0
    }
}
